idds/__init__.py
idds/doma/__init__.py
idds/doma/version.py
idds/doma/workflow/__init__.py
idds/doma/workflow/domapandawork.py
idds/doma/workflowv2/__init__.py
idds/doma/workflowv2/domaeventmap.py
idds/doma/workflowv2/domapandaeswork.py
idds/doma/workflowv2/domapandawork.py
idds/doma/workflowv2/domatree.py
idds_doma-2.0.9.data/data/tools/env/environment.yml
idds_doma-2.0.9.data/scripts/setup_panda_token
idds_doma-2.0.9.data/scripts/setup_panda_token.py
idds_doma-2.0.9.dist-info/LICENSE.rst
idds_doma-2.0.9.dist-info/METADATA
idds_doma-2.0.9.dist-info/WHEEL
idds_doma-2.0.9.dist-info/top_level.txt
idds_doma-2.0.9.dist-info/RECORD
